genericformat/__about__.py
genericformat/__init__.py
genericformat/__main__.py
genericformat/genericformat.py
genericformat-0.2.0.dist-info/METADATA
genericformat-0.2.0.dist-info/WHEEL
genericformat-0.2.0.dist-info/entry_points.txt
genericformat-0.2.0.dist-info/licenses/LICENSE
genericformat-0.2.0.dist-info/RECORD
