Metadata-Version: 2.1
Name: genericformat
Version: 0.2.0
Summary: A generic formatter
Project-URL: Source, https://github.com/waylonwalker/genericformat
Author-email: Waylon Walker <waylon@waylonwalker.com>
License: Copyright (c) 2012-2022 Waylon Walker
License-File: LICENSE
Classifier: Development Status :: 3 - Alpha
Classifier: Environment :: Console
Classifier: Intended Audience :: Developers
Classifier: Natural Language :: English
Classifier: Operating System :: OS Independent
Classifier: Programming Language :: Python
Classifier: Programming Language :: Python :: 3
Classifier: Programming Language :: Python :: 3 :: Only
Classifier: Programming Language :: Python :: 3.6
Classifier: Programming Language :: Python :: 3.7
Classifier: Programming Language :: Python :: 3.8
Classifier: Programming Language :: Python :: 3.9
Classifier: Programming Language :: Python :: 3.10
Classifier: Programming Language :: Python :: Implementation :: CPython
Classifier: Programming Language :: Python :: Implementation :: PyPy
Classifier: Topic :: Software Development
Classifier: Topic :: Text Processing
Classifier: Typing :: Typed
Requires-Python: >=3.6
